toggl_python/__init__.py
toggl_python/api.py
toggl_python/auth.py
toggl_python/entities/__init__.py
toggl_python/entities/report_time_entry.py
toggl_python/entities/user.py
toggl_python/entities/workspace.py
toggl_python/exceptions.py
toggl_python/schemas/__init__.py
toggl_python/schemas/base.py
toggl_python/schemas/current_user.py
toggl_python/schemas/project.py
toggl_python/schemas/report_time_entry.py
toggl_python/schemas/time_entry.py
toggl_python/schemas/workspace.py
toggl_python-0.3.1.dist-info/LICENSE
toggl_python-0.3.1.dist-info/METADATA
toggl_python-0.3.1.dist-info/WHEEL
toggl_python-0.3.1.dist-info/RECORD
