Metadata-Version: 2.1
Name: toggl_python
Version: 0.3.1
Summary: Typed `Toggl API` Python wrapper with pre-validation to avoid extra network usage.
Home-page: https://github.com/evrone/toggl_python
Author: Evrone
Author-email: mail@evrone.com
Maintainer: Nifadev Vadim
Maintainer-email: vnifadev@evrone.com
Requires-Python: >=3.8.18,<4.0.0
Classifier: Development Status :: 4 - Beta
Classifier: Intended Audience :: Developers
Classifier: License :: OSI Approved :: MIT License
Classifier: Natural Language :: English
Classifier: Operating System :: OS Independent
Classifier: Programming Language :: Python :: 3
Classifier: Programming Language :: Python :: 3.9
Classifier: Programming Language :: Python :: 3.10
Classifier: Programming Language :: Python :: 3.11
Classifier: Programming Language :: Python :: 3.12
Classifier: Programming Language :: Python :: 3 :: Only
Classifier: Programming Language :: Python :: 3.13
Classifier: Programming Language :: Python :: 3.8
Classifier: Typing :: Typed
Requires-Dist: backports-zoneinfo (>=0.2.1,<0.3.0) ; python_version == "3.8"
Requires-Dist: httpx[http2] (>=0.27.2,<0.28.0)
Requires-Dist: pydantic[email] (>=2.9.2,<3.0.0)
Project-URL: Documentation, https://toggl-python.readthedocs.io
Project-URL: Repository, https://github.com/evrone/toggl_python
